{"cameraMode":{"drawMode":0,"name":"Shaded","section":"Shading Mode"},"sceneLighting":false,"audioPlay":false,"sceneViewState":{"m_AlwaysRefresh":false,"showFog":true,"showSkybox":false,"showFlares":true,"showImageEffects":true,"showParticleSystems":true,"showVisualEffectGraphs":true,"m_FxEnabled":true},"in2DMode":false,"pivot":{"x":9.676129341125489,"y":6.111282825469971,"z":9.393050193786621},"rotation":{"x":-0.1021161898970604,"y":0.8977782130241394,"z":-0.2955224812030792,"w":-0.31022757291793826},"size":4.294345855712891,"orthographic":false}